Metadata-Version: 2.1
Name: fpgatools
Version: 1.2.0
Summary: University project to support FPGA development.
Home-page: https://github.com/Fint0r/FPGA_Tools
Author: József Fintor
Author-email: fintor976@gmail.com
License: MIT
Keywords: fpga,development,xdc,testbench,generator,tb
Platform: UNKNOWN
Classifier: Development Status :: 4 - Beta
Classifier: Intended Audience :: Education
Classifier: Operating System :: Microsoft :: Windows :: Windows 10
Classifier: Operating System :: POSIX :: Linux
Classifier: License :: OSI Approved :: MIT License
Classifier: Programming Language :: Python :: 3
